atags/__init__.py
atags/atags.py
atags/profile.py
atags-0.0.1.dist-info/LICENSE
atags-0.0.1.dist-info/METADATA
atags-0.0.1.dist-info/WHEEL
atags-0.0.1.dist-info/entry_points.txt
atags-0.0.1.dist-info/top_level.txt
atags-0.0.1.dist-info/RECORD
